prettifyJsonLog/__init__.py
prettifyJsonLog/prettifyJsonLog.py
prettifyJsonLog-1.0.3.dist-info/LICENSE
prettifyJsonLog-1.0.3.dist-info/METADATA
prettifyJsonLog-1.0.3.dist-info/WHEEL
prettifyJsonLog-1.0.3.dist-info/entry_points.txt
prettifyJsonLog-1.0.3.dist-info/top_level.txt
prettifyJsonLog-1.0.3.dist-info/RECORD
