Metadata-Version: 2.1
Name: prettifyJsonLog
Version: 1.0.3
Summary: A small python programm to make json log formats human readable
Home-page: https://github.com/neumantm/prettifyJsonLog
Author: Tim Neumann
Author-email: neuamntm@fius.informatik.uni-stuttgart.de
License: MIT
License-File: LICENSE
